MANIFEST.in
README.md
setup.py
baraag/__init__.py
baraag/baraag.py
baraag/cmdline.py
baraag/evernote.py
baraag/fsevents_wrapper.py
baraag/moo_wrapper.py
baraag.egg-info/PKG-INFO
baraag.egg-info/SOURCES.txt
baraag.egg-info/dependency_links.txt
baraag.egg-info/entry_points.txt
baraag.egg-info/requires.txt
baraag.egg-info/top_level.txt
baraag/tests/__init__.py
baraag/tests/runner.py
baraag/tests/test_evernote.py
baraag/tests/fixtures/image_content.enml
baraag/tests/fixtures/image_content.md
baraag/tests/fixtures/multibyte_content.enml
baraag/tests/fixtures/multibyte_content.md
baraag/tests/fixtures/simple_content.enml
baraag/tests/fixtures/simple_content.md