Metadata-Version: 1.0
Name: baraag
Version: 0.2
Summary: Markdown preview server work with Evernote in Mac
Home-page: https://github.com/orangain/baraag
Author: orangain
Author-email: orangain@gmail.com
License: MIT
Keywords: evernote,markdown,preview
Platform: Mac OS X
Classifier: Development Status :: 4 - Beta
Classifier: License :: OSI Approved :: MIT License
Classifier: Intended Audience :: Developers
Classifier: Intended Audience :: End Users/Desktop
Classifier: Operating System :: MacOS :: MacOS X
Classifier: Programming Language :: Python
Classifier: Programming Language :: Python :: 2
Classifier: Programming Language :: Python :: 2.7
Classifier: Topic :: Utilities
